iseqresources/__init__.py
iseqresources/add_new_tool_to_json.py
iseqresources/add_task_to_jira.py
iseqresources/add_tool.py
iseqresources/check_version.py
iseqresources/check_versions_add_task.py
iseqresources/docker_versions.py
iseqresources/update_docker_versions.py
iseqresources/update_record.py
iseqresources/update_tool_record.py
utils/__init__.py
utils/utils.py
iseqresources-0.0.15.dist-info/LICENSE
iseqresources-0.0.15.dist-info/METADATA
iseqresources-0.0.15.dist-info/WHEEL
iseqresources-0.0.15.dist-info/entry_points.txt
iseqresources-0.0.15.dist-info/top_level.txt
iseqresources-0.0.15.dist-info/RECORD
