Metadata-Version: 2.1
Name: iseqresources
Version: 0.0.15
Summary: Package for adding new tools to json file, checking their versions and creating tasks in JIRA
Home-page: https://gitlab.com/intelliseq/iseqresources
Author: Mateusz Marynowski, Olaf Tomaszewski
Author-email: mateusz.marynowski@intelliseq.pl, olaf.tomaszewski@intelliseq.pl
Classifier: Programming Language :: Python :: 3
Classifier: License :: OSI Approved :: MIT License
Classifier: Operating System :: OS Independent
Requires-Python: >=3.6
License-File: LICENSE
Requires-Dist: jira (>=3.3.0)
Requires-Dist: requests (>=2.22.0)
Requires-Dist: python-gitlab (>=3.7.0)
